decompyle3/__init__.py
decompyle3/code_fns.py
decompyle3/disas.py
decompyle3/linenumbers.py
decompyle3/main.py
decompyle3/scanner.py
decompyle3/show.py
decompyle3/util.py
decompyle3/version.py
decompyle3/bin/__init__.py
decompyle3/bin/decompile.py
decompyle3/bin/decompile_code_type.py
decompyle3/bin/decompile_tokens.py
decompyle3/parsers/__init__.py
decompyle3/parsers/dump.py
decompyle3/parsers/main.py
decompyle3/parsers/parse_heads.py
decompyle3/parsers/treenode.py
decompyle3/parsers/p37/__init__.py
decompyle3/parsers/p37/base.py
decompyle3/parsers/p37/full.py
decompyle3/parsers/p37/heads.py
decompyle3/parsers/p37/lambda_custom.py
decompyle3/parsers/p37/lambda_expr.py
decompyle3/parsers/p38/__init__.py
decompyle3/parsers/p38/base.py
decompyle3/parsers/p38/full.py
decompyle3/parsers/p38/full_custom.py
decompyle3/parsers/p38/heads.py
decompyle3/parsers/p38/lambda_custom.py
decompyle3/parsers/p38/lambda_expr.py
decompyle3/parsers/p38pypy/__init__.py
decompyle3/parsers/p38pypy/base.py
decompyle3/parsers/p38pypy/full.py
decompyle3/parsers/p38pypy/full_custom.py
decompyle3/parsers/p38pypy/heads.py
decompyle3/parsers/p38pypy/lambda_custom.py
decompyle3/parsers/p38pypy/lambda_expr.py
decompyle3/parsers/reduce_check/__init__.py
decompyle3/parsers/reduce_check/and_check.py
decompyle3/parsers/reduce_check/and_cond_check.py
decompyle3/parsers/reduce_check/and_not_check.py
decompyle3/parsers/reduce_check/break38_check.py
decompyle3/parsers/reduce_check/c_tryelsestmt.py
decompyle3/parsers/reduce_check/for38_check.py
decompyle3/parsers/reduce_check/forelse38_check.py
decompyle3/parsers/reduce_check/if_and_elsestmt.py
decompyle3/parsers/reduce_check/if_and_stmt.py
decompyle3/parsers/reduce_check/if_not_stmtc.py
decompyle3/parsers/reduce_check/ifelsestmt.py
decompyle3/parsers/reduce_check/iflaststmt.py
decompyle3/parsers/reduce_check/ifstmt.py
decompyle3/parsers/reduce_check/ifstmts_jump.py
decompyle3/parsers/reduce_check/joined_str_check.py
decompyle3-3.9.2.dist-info/COPYING
decompyle3-3.9.2.dist-info/METADATA
decompyle3-3.9.2.dist-info/WHEEL
decompyle3-3.9.2.dist-info/entry_points.txt
decompyle3-3.9.2.dist-info/top_level.txt
decompyle3-3.9.2.dist-info/zip-safe
decompyle3-3.9.2.dist-info/RECORD
