Metadata-Version: 2.1
Name: decompyle3
Version: 3.9.2
Summary: Python cross-version byte-code decompiler
Home-page: https://github.com/rocky/python-decompile3/
Author: Rocky Bernstein, Hartmut Goebel, John Aycock, and others
Author-email: rb@dustyfeet.com
License: GPL3
Classifier: Development Status :: 5 - Production/Stable
Classifier: Intended Audience :: Developers
Classifier: License :: OSI Approved :: GNU General Public License v3 (GPLv3)
Classifier: Operating System :: OS Independent
Classifier: Programming Language :: Python :: 3.7
Classifier: Programming Language :: Python :: 3.8
Classifier: Programming Language :: Python :: Implementation :: PyPy
Classifier: Topic :: Software Development :: Debuggers
Classifier: Topic :: Software Development :: Libraries :: Python Modules
License-File: COPYING
